apwgsdk
