Metadata-Version: 1.1
Name: apwgsdk
Version: 1.0
Summary: APWG Software Development Kid
Home-page: https://github.com/csirtgadgets/apwgsdk-py
Author: Wes Young
Author-email: wes@csirtgadgets.org
License: MPL2
Keywords: network,security
Platform: UNKNOWN
Classifier: Topic :: System :: Networking
Classifier: Intended Audience :: Developers
Classifier: License :: OSI Approved :: Mozilla Public License 2.0 (MPL 2.0)
